privex/__init__.py
privex/loghelper/LogHelper.py
privex/loghelper/__init__.py
privex_loghelper-1.1.3.dist-info/LICENSE
privex_loghelper-1.1.3.dist-info/METADATA
privex_loghelper-1.1.3.dist-info/WHEEL
privex_loghelper-1.1.3.dist-info/top_level.txt
privex_loghelper-1.1.3.dist-info/RECORD
