Metadata-Version: 2.1
Name: privex-loghelper
Version: 1.1.3
Summary: Small dependency-free class to make logging easier
Home-page: https://github.com/Privex/python-loghelper
Author: Chris (Someguy123) @ Privex
Author-email: chris@privex.io
License: MIT
Platform: UNKNOWN
Classifier: Programming Language :: Python :: 3
Classifier: Programming Language :: Python :: 3.7
Classifier: Programming Language :: Python :: 3.6
Classifier: Programming Language :: Python :: 3.4
Classifier: Programming Language :: Python :: 2.7
Classifier: Programming Language :: Python :: 2
Classifier: License :: OSI Approved :: MIT License
Classifier: Operating System :: OS Independent
Provides-Extra: concurrent
Requires-Dist: ConcurrentLogHandler ; extra == 'concurrent'
Provides-Extra: concurrent3
Requires-Dist: concurrent-log-handler ; extra == 'concurrent3'
